QtMkEditor/__init__.py
QtMkEditor/core/__init__.py
QtMkEditor/core/vars.py
QtMkEditor/core/control/__init__.py
QtMkEditor/core/control/markdownToHtml.py
QtMkEditor/core/control/menuBar.py
QtMkEditor/core/control/textControl.py
QtMkEditor/core/view/__init__.py
QtMkEditor/core/view/mainWidget.py
QtMkEditor/core/view/menuBar.py
QtMkEditor/core/view/text_area.py
QtMkEditor/core/view/toolBar.py
QtMkEditor/core/view/icons/__init__.py
QtMkEditor/core/view/icons/bold.png
QtMkEditor/core/view/icons/cancel.png
QtMkEditor/core/view/icons/code.png
QtMkEditor/core/view/icons/heading.png
QtMkEditor/core/view/icons/image.png
QtMkEditor/core/view/icons/italic.png
QtMkEditor/core/view/icons/link.png
QtMkEditor/core/view/icons/open.png
QtMkEditor/core/view/icons/save.png
QtMkEditor/core/view/icons/table.png
QtMkEditor/core/view/icons/underline.png
QtMkEditor/core/view/style/__init__.py
QtMkEditor/core/view/style/menubar.qss
QtMkEditor/core/view/style/style.css
QtMkEditor/core/view/style/style.qss
QtMkEditor/core/view/ui/__init__.py
QtMkEditor/core/view/ui/mainwidget.ui
QtMkEditor-1.0.0.dist-info/LICENCE.txt
QtMkEditor-1.0.0.dist-info/METADATA
QtMkEditor-1.0.0.dist-info/WHEEL
QtMkEditor-1.0.0.dist-info/top_level.txt
QtMkEditor-1.0.0.dist-info/RECORD
