Metadata-Version: 2.1
Name: QtMkEditor
Version: 1.0.0
Summary: Markdown Editor.
Home-page: 
Author: Moussa JAMOR
Author-email: moussajamorsup@gmail.com
License: MIT
Keywords: Markdown,Html,Editor,PyQt5
Classifier: Programming Language :: Python :: 3
Classifier: License :: OSI Approved :: MIT License
Classifier: Operating System :: OS Independent
License-File: LICENCE.txt
Requires-Dist: PyQt5
Requires-Dist: markdown
Requires-Dist: bs4
